unitscalar/UnitScalar.py
unitscalar/__init__.py
unitscalar-0.0.10.dist-info/METADATA
unitscalar-0.0.10.dist-info/WHEEL
unitscalar-0.0.10.dist-info/licenses/LICENSE.txt
unitscalar-0.0.10.dist-info/RECORD
