Metadata-Version: 2.4
Name: unitscalar
Version: 0.0.10
Summary: A package for dimensional analysis calculations on floating-point values
Project-URL: Homepage, https://github.com/neilbalch/unitscalar
Project-URL: Issues, https://github.com/neilbalch/unitscalar/issues
Author-email: Neil Balch <neilbalch@gmail.com>
License-File: LICENSE.txt
Classifier: Intended Audience :: Science/Research
Classifier: License :: OSI Approved :: MIT License
Classifier: Operating System :: OS Independent
Classifier: Programming Language :: Python :: 3
Classifier: Topic :: Scientific/Engineering
Requires-Python: >=3.8
Requires-Dist: custom-literals
Requires-Dist: forbiddenfruit
